{
  "lifetime": {
    "status": "ok",
    "method": "leave-one-out k-NN cross-validation",
    "k": 50,
    "total_samples": 8000,
    "buckets_used": 8,
    "n_curves_indexed": 70823,
    "thresholds": {
      "50": {
        "threshold_pct": 50,
        "n": 229,
        "n_graduated": 194,
        "actual_grad_rate": 0.8471615720524017
      },
      "60": {
        "threshold_pct": 60,
        "n": 185,
        "n_graduated": 173,
        "actual_grad_rate": 0.9351351351351351
      },
      "70": {
        "threshold_pct": 70,
        "n": 151,
        "n_graduated": 144,
        "actual_grad_rate": 0.9536423841059603
      },
      "80": {
        "threshold_pct": 80,
        "n": 124,
        "n_graduated": 123,
        "actual_grad_rate": 0.9919354838709677
      },
      "90": {
        "threshold_pct": 90,
        "n": 99,
        "n_graduated": 99,
        "actual_grad_rate": 1.0
      }
    },
    "computed_at": 1777411773,
    "next_recompute_at": 1777433373
  },
  "forward": {
    "status": "ok",
    "method": "forward production predictions, resolved against observer flush",
    "tracking_since": 1777401979,
    "predictions_total": 1830,
    "thresholds": {
      "50": {
        "threshold_pct": 50,
        "n_total": 1830,
        "n_pending": 587,
        "n_resolved": 1243,
        "n_graduated": 1052,
        "actual_grad_rate": 0.8463395012067578
      },
      "60": {
        "threshold_pct": 60,
        "n_total": 1395,
        "n_pending": 441,
        "n_resolved": 954,
        "n_graduated": 886,
        "actual_grad_rate": 0.9287211740041929
      },
      "70": {
        "threshold_pct": 70,
        "n_total": 1190,
        "n_pending": 377,
        "n_resolved": 813,
        "n_graduated": 784,
        "actual_grad_rate": 0.964329643296433
      },
      "80": {
        "threshold_pct": 80,
        "n_total": 1010,
        "n_pending": 307,
        "n_resolved": 703,
        "n_graduated": 692,
        "actual_grad_rate": 0.984352773826458
      },
      "90": {
        "threshold_pct": 90,
        "n_total": 875,
        "n_pending": 263,
        "n_resolved": 612,
        "n_graduated": 605,
        "actual_grad_rate": 0.988562091503268
      }
    },
    "computed_at": 1777411811
  }
}